elizur/__init__.py
elizur-0.2.2.dist-info/licenses/LICENSE.txt
elizur-0.2.2.dist-info/METADATA
elizur-0.2.2.dist-info/WHEEL
elizur-0.2.2.dist-info/top_level.txt
elizur-0.2.2.dist-info/RECORD
